fontmat/__init__.py
fontmat/cli/__init__.py
fontmat/cli/constants.py
fontmat-0.1.0.dist-info/METADATA
fontmat-0.1.0.dist-info/WHEEL
fontmat-0.1.0.dist-info/entry_points.txt
fontmat-0.1.0.dist-info/licenses/LICENSE
fontmat-0.1.0.dist-info/RECORD
