Metadata-Version: 2.3
Name: fontmat
Version: 0.1.0
Summary: A CLI to check font metadata.
Project-URL: Issues, https://gitlab.com/joaommpalmeiro/fontmat/-/issues
Project-URL: Source, https://gitlab.com/joaommpalmeiro/fontmat
Author-email: João Palmeiro <joaopalmeiro@proton.me>
License-Expression: MIT
License-File: LICENSE
Classifier: Development Status :: 4 - Beta
Classifier: Environment :: Console
Classifier: Intended Audience :: Developers
Classifier: License :: OSI Approved :: MIT License
Classifier: Natural Language :: English
Classifier: Operating System :: OS Independent
Classifier: Programming Language :: Python
Classifier: Programming Language :: Python :: 3
Classifier: Programming Language :: Python :: 3 :: Only
Classifier: Programming Language :: Python :: 3.10
Classifier: Programming Language :: Python :: 3.11
Classifier: Programming Language :: Python :: 3.12
Classifier: Programming Language :: Python :: 3.13
Classifier: Programming Language :: Python :: Implementation :: CPython
Classifier: Topic :: Utilities
Requires-Python: >=3.10
Requires-Dist: click>=8.1.0
Requires-Dist: fonttools[woff]>=4.53.0
